saplexer/__init__.py
saplexer/display.py
saplexer/a/1.txt
saplexer/a/10.txt
saplexer/a/11.txt
saplexer/a/12.txt
saplexer/a/2.txt
saplexer/a/3.txt
saplexer/a/4.txt
saplexer/a/5.txt
saplexer/a/6.txt
saplexer/a/7.txt
saplexer/a/8.txt
saplexer/a/9.txt
saplexer/b/1.txt
saplexer/b/10.txt
saplexer/b/11.txt
saplexer/b/12.txt
saplexer/b/13.txt
saplexer/b/14.txt
saplexer/b/15.txt
saplexer/b/16.txt
saplexer/b/17.txt
saplexer/b/18.txt
saplexer/b/2.txt
saplexer/b/3.txt
saplexer/b/4.txt
saplexer/b/5.txt
saplexer/b/6.txt
saplexer/b/7.txt
saplexer/b/8.txt
saplexer/b/9.txt
saplexer-1.2.4.dist-info/licenses/LICENSE
saplexer-1.2.4.dist-info/METADATA
saplexer-1.2.4.dist-info/WHEEL
saplexer-1.2.4.dist-info/top_level.txt
saplexer-1.2.4.dist-info/RECORD
